CSST/CSST.py
CSST/_init_.py
csst_parameter-0.1.4.dist-info/METADATA
csst_parameter-0.1.4.dist-info/WHEEL
csst_parameter-0.1.4.dist-info/licenses/LICENSE
csst_parameter-0.1.4.dist-info/RECORD
