Metadata-Version: 2.1
Name: CSST_parameter
Version: 0.1.4
Summary: This package can be used to estimate the metallicity and effective temperature of the stars from the CSST broad-band filter systems
Project-URL: Homepage, https://github.com/191805/feh_CSST1
Author-email: Shi Ruifeng <shiruifeng23@mails.ucas.ac.cn>
License-File: LICENSE
Classifier: License :: OSI Approved :: MIT License
Classifier: Operating System :: OS Independent
Classifier: Programming Language :: Python :: 3
Requires-Python: >=3.7
